lektor_thumbnail_generator.py
lektor_thumbnail_generator-0.5.0.dist-info/METADATA
lektor_thumbnail_generator-0.5.0.dist-info/WHEEL
lektor_thumbnail_generator-0.5.0.dist-info/entry_points.txt
lektor_thumbnail_generator-0.5.0.dist-info/top_level.txt
lektor_thumbnail_generator-0.5.0.dist-info/RECORD
