Metadata-Version: 2.1
Name: lektor-thumbnail-generator
Version: 0.5.0
Summary: This plugin automatically generates thumbnails for any images in your Lektor content. The difference between this plugin and the `thumbnail` filter is that this is geared towards content, i.e. you don't need to have any references to the images in your templates at all.
Home-page: https://github.com/skorokithakis/lektor-thumbnail-generator/
Author: Stavros Korokithakis,,,
Author-email: hi@stavros.io
License: MIT
Platform: UNKNOWN
